README.rst
setup.cfg
setup.py
cute/__init__.py
cute/cute_reader.py
cute/cute_writer.py
cute_format.egg-info/PKG-INFO
cute_format.egg-info/SOURCES.txt
cute_format.egg-info/dependency_links.txt
cute_format.egg-info/top_level.txt
tests/test_cute.py