Metadata-Version: 1.1
Name: cute-format
Version: 0.1.3
Summary: pack data and retrieval in easy way
Home-page: https://github.com/twmht/cute_format
Author: Ming Hsuan Tu
Author-email: qrnnis2623891@gmail.com
License: MIT License
Platform: UNKNOWN
Classifier: Development Status :: 5 - Production/Stable
Classifier: Environment :: Console
Classifier: Intended Audience :: Developers
Classifier: License :: OSI Approved :: MIT License
Classifier: Operating System :: OS Independent
Classifier: Programming Language :: Python
Classifier: Programming Language :: Python :: 2
Classifier: Programming Language :: Python :: 2.6
Classifier: Programming Language :: Python :: 2.7
Classifier: Programming Language :: Python :: 3
Classifier: Programming Language :: Python :: 3.4
Classifier: Programming Language :: Python :: 3.5
Classifier: Topic :: Terminals
Classifier: Topic :: Utilities
